agentic_search/__init__.py
agentic_search/lib.py
agentic_search/capabilities/__init__.py
agentic_search/capabilities/arxiv.py
agentic_search/capabilities/sql.py
agentic_search/capabilities/text.py
agentic_search/capabilities/web.py
agentic_search/chains/__init__.py
agentic_search/chains/arxiv.py
agentic_search/chains/sql.py
agentic_search/chains/text.py
agentic_search/chains/web.py
agentic_search/functions/__init__.py
agentic_search/functions/arxiv.py
agentic_search/functions/sql.py
agentic_search/functions/test_text.py
agentic_search/functions/text.py
agentic_search/functions/web.py
agentic_search/graphs/__init__.py
agentic_search/graphs/web.py
agentic_search/nodes/__init__.py
agentic_search/nodes/web.py
agentic_search/prompts/__init__.py
agentic_search/prompts/arxiv.py
agentic_search/prompts/sql.py
agentic_search/prompts/text.py
agentic_search/prompts/web.py
agentic_search/tools/__init__.py
agentic_search/tools/web.py
agentic_search-12.0.1.dist-info/LICENSE
agentic_search-12.0.1.dist-info/METADATA
agentic_search-12.0.1.dist-info/WHEEL
agentic_search-12.0.1.dist-info/top_level.txt
agentic_search-12.0.1.dist-info/RECORD
