Metadata-Version: 2.1
Name: agentic_search
Version: 12.0.1
Summary: code for an agentic search tool using Langchain
Home-page: https://github.com/markets-agent/agentic-search
Author: yactouat
Author-email: yactouat@yactouat.com
License: MIT
License-File: LICENSE
Requires-Dist: aiocache
Requires-Dist: aiohttp
Requires-Dist: arxiv
Requires-Dist: asyncio
Requires-Dist: beautifulsoup4
Requires-Dist: duckduckgo-search
Requires-Dist: langchain-community
Requires-Dist: langchain-core
Requires-Dist: langchain-openai
Requires-Dist: langgraph
Requires-Dist: nltk
Requires-Dist: pydantic
Requires-Dist: pypdf
Requires-Dist: python-dotenv
Requires-Dist: redis
Requires-Dist: requests
Requires-Dist: selenium
Requires-Dist: yollama
Requires-Dist: ypostgres_lib
